axis42/Axis.py
axis42/Axis_api.py
axis42/User.py
axis42/__init__.py
axis42/settings.py
axis42/utils.py
Axis42-0.0.11.dist-info/LICENSE
Axis42-0.0.11.dist-info/METADATA
Axis42-0.0.11.dist-info/WHEEL
Axis42-0.0.11.dist-info/top_level.txt
Axis42-0.0.11.dist-info/RECORD
