Metadata-Version: 2.1
Name: Axis42
Version: 0.0.11
Summary: Axis wrapper class for controlling the school access for 42 students.
Author: 42-Portugal
Author-email: rm@42lisboa.com
License: Copyright (c) 2022 Drop
Project-URL: repository, https://github.com/42-Portugal/access_lisboa
Project-URL: Bug Tracker, https://github.com/42-Portugal/access_lisboa/issues
Classifier: Programming Language :: Python :: 3
Classifier: License :: OSI Approved :: MIT License
Classifier: Operating System :: OS Independent
Requires-Python: >=3.10
License-File: LICENSE
